{
  "revision": "v1.0",
  "name": "tstar.sim1",
  "items": [
    {
      "name": "TCS_GV_OPT_CARRIER_TYPE",
      "writes": [
        8195
      ]
    },
    {
      "name": "PSS.MMC.MMSS RAT ID",
      "writes": [
        2,
        9,
        3,
        5,
        2,
        4,
        0,
        0
      ]
    },
    {
      "name": "TCS_GV_FCN_DUAL_PDP_SUPPORT",
      "writes": [
        1
      ]
    },
    {
      "name": "HCOMMON.Support of Quick Rollback To LTE",
      "writes": [
        2
      ]
    },
    {
      "name": "HCOMMON.Support of Quick Rollback G2L",
      "writes": [
        1
      ]
    },
    {
      "name": "NASL3.MM.gprs_multislot_class",
      "writes": [
        12
      ]
    },
    {
      "name": "NASL3.MM.A5_algorithms",
      "writes": [
        1,
        0,
        1,
        1,
        0,
        0,
        0
      ]
    },
    {
      "name": "NR.CONFIG.MODE",
      "writes": [
        1
      ]
    },
    {
      "name": "NASU.NR.CONFIG.MODE",
      "writes": [
        1
      ]
    },
    {
      "name": "PSS.GMC_NrRoamingDisableType",
      "writes": [
        10
      ]
    },
    {
      "name": "!NRCAPA.Switch.DssFeature",
      "writes": [
        1
      ]
    },
    {
      "name": "!NRCAPA.Gen.DynamicPowerSharing",
      "writes": [
        1
      ]
    },
    {
      "name": "UECAPA_NR_RF_BAND_FR1_BM",
      "writes": [
        49354
      ]
    },
    {
      "name": "UECAPA_NR_RF_BAND_FR2_BM",
      "writes": [
        49354
      ]
    },
    {
      "name": "UECAPA_NR_RF_BAND_21_FBI",
      "writes": [
        0
      ]
    },
    {
      "name": "UECAPA_NR_RF_BAND_22_FBI",
      "writes": [
        0
      ]
    },
    {
      "name": "UECAPA_NR_RF_BAND_23_FBI",
      "writes": [
        0
      ]
    },
    {
      "name": "UECAPA_NR_RF_BAND_24_FBI",
      "writes": [
        0
      ]
    },
    {
      "name": "NASU.SUPPORTED.EMC.IMS",
      "writes": [
        2
      ]
    },
    {
      "name": "PSS.AIMS.Operator-Spec",
      "writes": [
        141
      ]
    },
    {
      "name": "PSS.AIMS.DYNAMIC_OPERATORSPEC_FLAG",
      "writes": [
        0
      ]
    },
    {
      "name": "PSS.AIMS.Payload-AMRNB",
      "writes": "fl"
    },
    {
      "name": "PSS.AIMS.Payload-AMRWB",
      "writes": "hn"
    },
    {
      "name": "PSS.AIMS.Conference.SUBSCRIBE-ENABLE",
      "writes": [
        0
      ]
    },
    {
      "name": "PSS.AIMS.EMC-PRECONDITION-ENABLE",
      "writes": [
        0
      ]
    },
    {
      "name": "PSS.AIMS.Video Precondtion QOS Enable",
      "writes": [
        0
      ]
    },
    {
      "name": "PSS.AIMS.SRVCC",
      "writes": [
        0
      ]
    },
    {
      "name": "PSS.AIMS.ALERTING_SRVCC",
      "writes": [
        0
      ]
    },
    {
      "name": "PSS.AIMS.PREALERTING_SRVCC",
      "writes": [
        0
      ]
    },
    {
      "name": "PSS.AIMS.MIDCALL_SRVCC",
      "writes": [
        0
      ]
    },
    {
      "name": "PSS.AIMS.Audio.Capability",
      "writes": [
        1
      ]
    },
    {
      "name": "PSS.AIMS.Min.Se",
      "writes": [
        1800
      ]
    },
    {
      "name": "PSS.AIMS.Ringback.Timer",
      "writes": [
        35
      ]
    },
    {
      "name": "PSS.AIMS.Ringing.Timer",
      "writes": [
        45
      ]
    },
    {
      "name": "PSS.AIMS.Timer.T4",
      "writes": [
        20000
      ]
    },
    {
      "name": "PSS.AIMS.Timer.J(64*T1 for UDP)",
      "writes": [
        32000
      ]
    },
    {
      "name": "PSS.AIMS.MT.USSD.Support",
      "writes": [
        0
      ]
    },
    {
      "name": "PSS.GMC_Emc_Wait_For_Lte_Attach_Enabled",
      "writes": [
        2
      ]
    }
  ]
}